LICENSE
README.md
setup.py
biobb_netprop/__init__.py
biobb_netprop.egg-info/PKG-INFO
biobb_netprop.egg-info/SOURCES.txt
biobb_netprop.egg-info/dependency_links.txt
biobb_netprop.egg-info/requires.txt
biobb_netprop.egg-info/top_level.txt
biobb_netprop/netprop/__init__.py
biobb_netprop/netprop/call_netprop.py
biobb_netprop/netprop/common.py
biobb_netprop/netprop/da_disgenet.py
biobb_netprop/netprop/dda_disgenet.py
biobb_netprop/netprop/ga_disgenet.py
biobb_netprop/netprop/gda_disgenet.py
biobb_netprop/netprop/maknodes.py
biobb_netprop/netprop/parsehippie.py
biobb_netprop/netprop/pre_common.py
biobb_netprop/netprop/previous_common.py
biobb_netprop/netprop/va_disgenet.py
biobb_netprop/netprop/vda_disgenet.py
biobb_netprop/template/__init__.py
biobb_netprop/template/template.py
biobb_netprop/template/template_container.py
biobb_netprop/test/__init__.py