Metadata-Version: 2.1
Name: biobb-netprop
Version: 1.12.3
Summary: Biobb_NetProp is use case to build a prioritize PPI Network through Disc4All pre-process database REST API.
Home-page: https://github.com/mapoferri/Biobb_NetProp
Author: Biobb developers - Maria Paola Ferri
Author-email: maria.ferri@bsc.es
Project-URL: Documentation, http://biobb_netprop.readthedocs.io/en/latest/
Project-URL: Bioexcel, https://bioexcel.eu/
Keywords: Bioinformatics Workflows BioExcel Compatibility
Classifier: Development Status :: 3 - Alpha
Classifier: Programming Language :: Python :: 3.7
Classifier: License :: OSI Approved :: Apache Software License
Classifier: Operating System :: MacOS :: MacOS X
Classifier: Operating System :: POSIX
Requires-Python: ==3.7.*
License-File: LICENSE
